gml/__init__.py
gml/_utils.py
gml/asset_manager.py
gml/client.py
gml/compile.py
gml/device.py
gml/hf.py
gml/model.py
gml/model_utils.py
gml/pipelines.py
gml/preprocessing.py
gml/proto/gogoproto/gogo_pb2.py
gml/proto/mediapipe/framework/calculator_contract_test_pb2.py
gml/proto/mediapipe/framework/calculator_options_pb2.py
gml/proto/mediapipe/framework/calculator_pb2.py
gml/proto/mediapipe/framework/calculator_profile_pb2.py
gml/proto/mediapipe/framework/mediapipe_options_pb2.py
gml/proto/mediapipe/framework/packet_factory_pb2.py
gml/proto/mediapipe/framework/packet_generator_pb2.py
gml/proto/mediapipe/framework/packet_test_pb2.py
gml/proto/mediapipe/framework/status_handler_pb2.py
gml/proto/mediapipe/framework/stream_handler_pb2.py
gml/proto/mediapipe/framework/test_calculators_pb2.py
gml/proto/mediapipe/framework/thread_pool_executor_pb2.py
gml/proto/opentelemetry/proto/common/v1/common_pb2.py
gml/proto/opentelemetry/proto/metrics/v1/metrics_pb2.py
gml/proto/opentelemetry/proto/resource/v1/resource_pb2.py
gml/proto/src/api/corepb/v1/actor_net_pb2.py
gml/proto/src/api/corepb/v1/compiled_pipeline_pb2.py
gml/proto/src/api/corepb/v1/controlplane_pb2.py
gml/proto/src/api/corepb/v1/cp_dp_pb2.py
gml/proto/src/api/corepb/v1/cp_edge_pb2.py
gml/proto/src/api/corepb/v1/dataplane_pb2.py
gml/proto/src/api/corepb/v1/deployed_pipeline_pb2.py
gml/proto/src/api/corepb/v1/device_info_pb2.py
gml/proto/src/api/corepb/v1/gem_config_pb2.py
gml/proto/src/api/corepb/v1/mediastream_pb2.py
gml/proto/src/api/corepb/v1/model_exec_pb2.py
gml/proto/src/common/typespb/jwt_pb2.py
gml/proto/src/common/typespb/status_pb2.py
gml/proto/src/common/typespb/uuid_pb2.py
gml/proto/src/controlplane/compiler/cpb/v1/cpb_pb2.py
gml/proto/src/controlplane/compiler/cpb/v1/cpb_pb2_grpc.py
gml/proto/src/controlplane/directory/directorypb/v1/directory_pb2.py
gml/proto/src/controlplane/directory/directorypb/v1/directory_pb2_grpc.py
gml/proto/src/controlplane/filetransfer/ftpb/v1/ftpb_pb2.py
gimlet_api-0.0.16.dist-info/WHEEL
gimlet_api-0.0.16.dist-info/METADATA
gimlet_api-0.0.16.dist-info/RECORD
